MANIFEST.in
README.md
setup.cfg
setup.py
common/__init__.py
common/error.py
common/exceptions.py
common/version.py
common/serializers/__init__.py
common/serializers/base58_serializer.py
common/serializers/base64_serializer.py
common/serializers/compact_serializer.py
common/serializers/field.py
common/serializers/json_serializer.py
common/serializers/mapping_serializer.py
common/serializers/msgpack_serializer.py
common/serializers/serialization.py
common/serializers/signing_serializer.py
common/serializers/stream_serializer.py
common/test/__init__.py
common/test/test_compact_serializer.py
common/test/test_exceptions.py
common/test/test_fields.py
common/test/test_json_serializer.py
common/test/test_msgpack_serializer.py
common/test/test_signing_serializer.py
common/test/version/__init__.py
common/test/version/test_version.py
crypto/__init__.py
crypto/bls/__init__.py
crypto/bls/bls_bft.py
crypto/bls/bls_bft_replica.py
crypto/bls/bls_crypto.py
crypto/bls/bls_factory.py
crypto/bls/bls_key_manager.py
crypto/bls/bls_key_register.py
crypto/bls/bls_multi_signature.py
crypto/bls/indy_crypto/__init__.py
crypto/bls/indy_crypto/bls_crypto_indy_crypto.py
crypto/test/__init__.py
crypto/test/test_multi_signature.py
crypto/test/bls/__init__.py
crypto/test/bls/indy_crypto/__init__.py
crypto/test/bls/indy_crypto/test_bls_crypto_indy_crypto.py
data/__init__.py
data/domain_transactions_local_genesis
data/domain_transactions_sandbox_genesis
data/pool_transactions_local_genesis
data/pool_transactions_sandbox_genesis
indy_plenum_dev.egg-info/PKG-INFO
indy_plenum_dev.egg-info/SOURCES.txt
indy_plenum_dev.egg-info/dependency_links.txt
indy_plenum_dev.egg-info/requires.txt
indy_plenum_dev.egg-info/top_level.txt
ledger/__init__.py
ledger/compact_merkle_tree.py
ledger/error.py
ledger/immutable_store.py
ledger/ledger.py
ledger/merkle_tree.py
ledger/merkle_verifier.py
ledger/tree_hasher.py
ledger/util.py
ledger/genesis_txn/__init__.py
ledger/genesis_txn/genesis_txn_file_util.py
ledger/genesis_txn/genesis_txn_initiator.py
ledger/genesis_txn/genesis_txn_initiator_from_file.py
ledger/hash_stores/__init__.py
ledger/hash_stores/file_hash_store.py
ledger/hash_stores/hash_store.py
